py_rfidpos_proto-1.0.0_alpha.dist-info/METADATA
py_rfidpos_proto-1.0.0_alpha.dist-info/WHEEL
py_rfidpos_proto.cpython-38-x86_64-linux-gnu.so
py_rfidpos_proto-1.0.0_alpha.dist-info/RECORD
