Metadata-Version: 2.1
Name: py-rfidpos-proto
Version: 1.0.0-alpha
Classifier: License :: OSI Approved :: MIT License
Classifier: Development Status :: 3 - Alpha
Classifier: Intended Audience :: Developers
Classifier: Programming Language :: Python
Classifier: Programming Language :: Rust
Classifier: Operating System :: POSIX
Classifier: Operating System :: MacOS :: MacOS X
Summary: Library to read/write RFID Positioning protocol.
Author: Aditya Kresna <aditya.kresna@outlook.co.id>
Author-Email: Aditya Kresna <aditya.kresna@outlook.co.id>
Maintainer: Aditya Kresna
Maintainer-Email: aditya.kresna@outlook.co.id
License: MIT
